editor/__init__.py
editor/_version.py
editor/editor.py
py_curses_editor-1.3.2.data/data/share/doc/py_curses_editor/CHANGELOG.md
py_curses_editor-1.3.2.data/data/share/doc/py_curses_editor/LICENSE.txt
py_curses_editor-1.3.2.data/data/share/doc/py_curses_editor/README.md
py_curses_editor-1.3.2.dist-info/METADATA
py_curses_editor-1.3.2.dist-info/WHEEL
py_curses_editor-1.3.2.dist-info/licenses/LICENSE.txt
py_curses_editor-1.3.2.dist-info/RECORD
