Metadata-Version: 2.1
Name: py-curses-editor
Version: 1.3.2
Summary: A configurable curses text editor window
Project-URL: Homepage, https://github.com/firecat53/py_curses_editor
Author-email: Scott Hansen <tech@firecat53.net>
License-File: LICENSE.txt
Keywords: console,curses,editor,utility
Classifier: Development Status :: 4 - Beta
Classifier: Environment :: Console
Classifier: Environment :: Console :: Curses
Classifier: Intended Audience :: Developers
Classifier: Intended Audience :: End Users/Desktop
Classifier: License :: OSI Approved :: MIT License
Classifier: Operating System :: OS Independent
Classifier: Programming Language :: Python
Classifier: Programming Language :: Python :: 3
Classifier: Topic :: Text Editors
Classifier: Topic :: Utilities
